tests/__init__.py
tests/conftest.py
tests/fixture/__init__.py
tests/testfiles/__init__.py
toolkit/__init__.py
toolkit/config.py
toolkit/filetype.py
toolkit/struct.py
toolkit/tpl.py
toolkit/ulib.py
toolkit/utils.py
toolkit-0.0.3.dist-info/DESCRIPTION.rst
toolkit-0.0.3.dist-info/entry_points.txt
toolkit-0.0.3.dist-info/METADATA
toolkit-0.0.3.dist-info/metadata.json
toolkit-0.0.3.dist-info/pbr.json
toolkit-0.0.3.dist-info/RECORD
toolkit-0.0.3.dist-info/top_level.txt
toolkit-0.0.3.dist-info/WHEEL
