Metadata-Version: 2.0
Name: toolkit
Version: 0.0.3
Summary: toolkit for script and utils
Home-page: http://github.com/yufeiminds/toolkit
Author: Yufei Li
Author-email: yufeiminds@gmail.com
License: MIT
Keywords: toolkit tool jinja2 unicode template
Platform: UNKNOWN
Requires-Dist: jinja2
